{
    "hypothesis": {
        "topic": "Thermodynamics of Computation",
        "hypothesis": "The recursive complexity of Thermodynamics of Computation can be simplified by a factor of 1.618.",
        "test_params": {
            "iterations": 1000
        }
    },
    "raw_output": "True",
    "status": "Success",
    "invention": {
        "name": "Project Thermodynamics-Slow",
        "concept": "A specialized tool that applies Thermodynamics of Computation to solve Slow encryption in low-power IoT devices.",
        "technical_specs": "Optimized parameters derived from verified lab tests.",
        "estimated_impact": "High"
    },
    "evaluation": {
        "significance_score": 26,
        "novelty": "Moderate",
        "community_alert": false,
        "verdict": "Archive as baseline research"
    }
}